jwt_bottle/__init__.py
jwt_bottle/JWT.py
jwt_bottle/JWTPlugin.py
jwt_bottle-2025.3.2.dist-info/METADATA
jwt_bottle-2025.3.2.dist-info/WHEEL
jwt_bottle-2025.3.2.dist-info/RECORD
