Metadata-Version: 2.3
Name: jwt_bottle
Version: 2025.3.2
Summary: Make easy using JWT authenticate on your project.
Author: Afonso Medeiros
Requires-Python: >=3.13
Classifier: Programming Language :: Python :: 3
Classifier: Programming Language :: Python :: 3.13
Requires-Dist: bottle (>=0.13.2,<0.14.0)
Requires-Dist: python-jose (>=3.4.0,<4.0.0)
